jrdf/__main__.py
jrdf-1.2.dist-info/METADATA
jrdf-1.2.dist-info/WHEEL
jrdf-1.2.dist-info/entry_points.txt
jrdf-1.2.dist-info/top_level.txt
jrdf-1.2.dist-info/RECORD
