Metadata-Version: 2.4
Name: jrdf
Version: 1.2
Summary: Just Rename the Damn Files
Author: 0000FF
Project-URL: Source, https://github.com/SimoneFelici/jrdf
Requires-Python: >=3.7
Requires-Dist: guessit
